Metadata-Version: 2.1
Name: europlexo
Version: 2.2.3
Summary: A python module to download tv series from magic
Home-page: https://github.com/mortafix/EuroPlexo
Author: Moris Doratiotto
Author-email: moris.doratiotto@gmail.com
License: UNKNOWN
Keywords: serie,tv,download
Platform: UNKNOWN
Classifier: Programming Language :: Python :: 3.8
Classifier: License :: OSI Approved :: MIT License
Classifier: Operating System :: OS Independent
Classifier: Development Status :: 3 - Alpha
Classifier: Intended Audience :: Developers
Requires-Python: >=3.8
